merge_csv.py
merge_csv-0.1.1.dist-info/entry_points.txt
merge_csv-0.1.1.dist-info/LICENSE
merge_csv-0.1.1.dist-info/WHEEL
merge_csv-0.1.1.dist-info/METADATA
merge_csv-0.1.1.dist-info/RECORD
